hugh_game.py
hugh_game-0.1.data/data/pgzero/data/icon.png
hugh_game-0.1.data/data/pgzero/data/joypad.png
pgzero/__init__.py
pgzero/__main__.py
pgzero/actor.py
pgzero/animation.py
pgzero/builtins.py
pgzero/clock.py
pgzero/constants.py
pgzero/game.py
pgzero/keyboard.py
pgzero/loaders.py
pgzero/music.py
pgzero/ptext.py
pgzero/rect.py
pgzero/runner.py
pgzero/screen.py
pgzero/soundfmt.py
pgzero/spellcheck.py
pgzero/tone.py
pgzero/data/icon.png
pgzero/data/joypad.png
hugh_game-0.1.dist-info/METADATA
hugh_game-0.1.dist-info/WHEEL
hugh_game-0.1.dist-info/entry_points.txt
hugh_game-0.1.dist-info/top_level.txt
hugh_game-0.1.dist-info/RECORD
